java_coder-0.0.5.dist-info/licenses/LICENSE.txt
javacoder/__init__.py
javacoder/core/__init__.py
javacoder/core/builder.py
javacoder/core/java_generator.py
javacoder/core/operator.py
javacoder/core/plugins.py
javacoder/project/__init__.py
javacoder/project/project.py
javacoder/utils/__init__.py
javacoder/utils/config.py
javacoder/utils/converter.py
javacoder/utils/generator.py
javacoder/utils/loader.py
javacoder/utils/log.py
java_coder-0.0.5.dist-info/METADATA
java_coder-0.0.5.dist-info/WHEEL
java_coder-0.0.5.dist-info/top_level.txt
java_coder-0.0.5.dist-info/RECORD
