Metadata-Version: 2.4
Name: java-coder
Version: 0.0.5
Summary: A java class file operate tools
Home-page: https://github.com/chonmb/javacoder
Author: chonmb
Author-email: weichonmb@foxmail.com
License: MIT
Requires-Python: >=3.6
License-File: LICENSE.txt
Requires-Dist: javalang
Requires-Dist: requests
Dynamic: author
Dynamic: author-email
Dynamic: description
Dynamic: description-content-type
Dynamic: home-page
Dynamic: license
Dynamic: license-file
Dynamic: requires-dist
Dynamic: requires-python
Dynamic: summary
